ml_dtypes/_finfo.py
ml_dtypes/_ml_dtypes_ext.cpython-311-aarch64-linux-gnu.so
ml_dtypes/_iinfo.py
ml_dtypes/__init__.py
ml_dtypes/py.typed
ml_dtypes-0.5.0.dist-info/WHEEL
ml_dtypes-0.5.0.dist-info/LICENSE.eigen
ml_dtypes-0.5.0.dist-info/LICENSE
ml_dtypes-0.5.0.dist-info/RECORD
ml_dtypes-0.5.0.dist-info/METADATA
ml_dtypes-0.5.0.dist-info/AUTHORS
ml_dtypes-0.5.0.dist-info/top_level.txt
