Metadata-Version: 2.1
Name: ml_dtypes
Version: 0.5.0
Author-email: ml_dtypes authors <ml_dtypes@google.com>
License: 
Project-URL: homepage, https://github.com/jax-ml/ml_dtypes
Project-URL: repository, https://github.com/jax-ml/ml_dtypes
Classifier: Programming Language :: Python :: 3
Classifier: Programming Language :: Python :: 3 :: Only
Classifier: License :: OSI Approved :: Apache Software License
Classifier: Intended Audience :: Science/Research
Requires-Python: >=3.9
License-File: LICENSE
License-File: LICENSE.eigen
License-File: AUTHORS
Requires-Dist: numpy>=1.21
Requires-Dist: numpy>=1.21.2; python_version >= "3.10"
Requires-Dist: numpy>=1.23.3; python_version >= "3.11"
Requires-Dist: numpy>=1.26.0; python_version >= "3.12"
Requires-Dist: numpy>=2.1.0; python_version >= "3.13"
Provides-Extra: dev
Requires-Dist: absl-py; extra == "dev"
Requires-Dist: pytest; extra == "dev"
Requires-Dist: pytest-xdist; extra == "dev"
Requires-Dist: pylint>=2.6.0; extra == "dev"
Requires-Dist: pyink; extra == "dev"
